{"tokens": [{"rank": 1, "chainId": "0x1", "coinAddress": "0xf4308b0263723b121056938c2172868e408079d0", "imgURL": "https://d23exngyjlavgo.cloudfront.net/0x1_0xf4308b0263723b121056938c2172868e408079d0", "name": "CryoDAO", "symbol": "CRYO", "uniqueName": "cryo-dao-1", "price": 3.793397002582041, "price24HChange": 13.288891436790001, "moralisScore": 94, "buyPressure": 201551.42882964498, "twitterFollowerCount": 2339, "volume24H": 460849.8250603151, "categories": [], "blockTimestamp": 1682602427, "fullyDilutedValuation": 16177530.120450953, "hypeScore": 39, "marketCap": 8088763.149798094, "firstSeenRank": 3, "firstSeenPrice": 2.9334722925823207, "firstSeenTimestampInSeconds": 1731784501, "rankChange": 2, "firstSeenPricePercentChange": 29.31422642627836, "firstSeenMaxPricePercentageChange": 29.31422642627836}, {"rank": 2, "chainId": "0x1", "coinAddress": "0x0ebe30595a44e5288c24161ddfc1e9fa08e33a0c", "imgURL": "https://d23exngyjlavgo.cloudfront.net/0x1_0x0ebe30595a44e5288c24161ddfc1e9fa08e33a0c", "name": "Nyan Meme Coin", "symbol": "NYAN", "uniqueName": "nyan-meme-coin", "price": 4.612824451e-08, "price24HChange": 5.083564696722662, "moralisScore": 92, "buyPressure": 30364.288573592014, "twitterFollowerCount": 6038, "volume24H": 486913.962567324, "categories": ["Meme"], "blockTimestamp": 1683310223, "fullyDilutedValuation": 2841654.965158367, "hypeScore": 36, "marketCap": 2585906.018294114, "firstSeenRank": 9, "firstSeenPrice": 3.9299911131e-08, "firstSeenTimestampInSeconds": 1731968101, "rankChange": 7, "firstSeenPricePercentChange": 17.374933384044652, "firstSeenMaxPricePercentageChange": 17.374933384044652}, {"rank": 3, "chainId": "0x1", "coinAddress": "0xf3b9569f82b18aef890de263b84189bd33ebe452", "imgURL": "https://d23exngyjlavgo.cloudfront.net/0x1_0xf3b9569f82b18aef890de263b84189bd33ebe452", "name": "A Hunters Dream", "symbol": "CAW", "uniqueName": "a-hunters-dream-2", "price": 8.1353660574e-08, "price24HChange": 16.121822085532802, "moralisScore": 99, "buyPressure": 219149.481059545, "twitterFollowerCount": 0, "volume24H": 321120.59988433897, "categories": ["Platform-Based Utility Tokens", "Privacy Coins"], "blockTimestamp": 1649911285, "fullyDilutedValuation": 50182082.24959337, "hypeScore": 35, "marketCap": 47946396.612700276, "firstSeenRank": 1, "firstSeenPrice": 7.8588301946e-08, "firstSeenTimestampInSeconds": 1731968701, "rankChange": -2, "firstSeenPricePercentChange": 3.5187916770363046, "firstSeenMaxPricePercentageChange": 3.5187916770363046}, {"rank": 4, "chainId": "0x1", "coinAddress": "0x9ce115f0341ae5dabc8b477b74e83db2018a6f42", "imgURL": "https://d23exngyjlavgo.cloudfront.net/0x1_0x9ce115f0341ae5dabc8b477b74e83db2018a6f42", "name": "HairDAO Token", "symbol": "HAIR", "uniqueName": "hair-dao-token", "price": 113.16403127642312, "price24HChange": 40.65788922853815, "moralisScore": 96, "buyPressure": 184682.81271503802, "twitterFollowerCount": 2639, "volume24H": 311539.178338406, "categories": ["Platform-Based Utility Tokens"], "blockTimestamp": 1675927331, "fullyDilutedValuation": 168193435.33675006, "hypeScore": 31, "marketCap": 17816122.11635949, "firstSeenRank": 26, "firstSeenPrice": 85.97582078152898, "firstSeenTimestampInSeconds": 1731894901, "rankChange": 22, "firstSeenPricePercentChange": 31.62308919851015, "firstSeenMaxPricePercentageChange": 34.122853281089064}, {"rank": 5, "chainId": "0x2105", "coinAddress": "0x0c5142bc58f9a61ab8c3d2085dd2f4e550c5ce0b", "imgURL": "https://d23exngyjlavgo.cloudfront.net/0x2105_0x0c5142bc58f9a61ab8c3d2085dd2f4e550c5ce0b", "name": "RUSSELL", "symbol": "RUSSELL", "uniqueName": "russell-2", "price": 0.01969115469488539, "price24HChange": 43.93364588526296, "moralisScore": 85, "buyPressure": 138670.03629103198, "twitterFollowerCount": 363, "volume24H": 1837585.6914023783, "categories": [], "blockTimestamp": 1728610033, "fullyDilutedValuation": 13661931.905448223, "hypeScore": 31, "marketCap": 13661931.905448223, "firstSeenRank": 604, "firstSeenPrice": 0.01419726655716009, "firstSeenTimestampInSeconds": 1731962101, "rankChange": 599, "firstSeenPricePercentChange": 38.69680206120082, "firstSeenMaxPricePercentageChange": 38.69680206120082}, {"rank": 6, "chainId": "0x1", "coinAddress": "0x3ce1f6bd6b0aa7520a14018dcc2261b1371d7c1a", "imgURL": "https://d23exngyjlavgo.cloudfront.net/0x1_0x3ce1f6bd6b0aa7520a14018dcc2261b1371d7c1a", "name": "Corn", "symbol": "CORN", "uniqueName": "corn-13", "price": 0.006310821530754861, "price24HChange": 74.73158831521732, "moralisScore": 70, "buyPressure": 105893.431852956, "twitterFollowerCount": 351, "volume24H": 485448.7589448041, "categories": [], "blockTimestamp": 1726175951, "fullyDilutedValuation": 6462240.210033705, "hypeScore": 29, "marketCap": 6462240.210033705, "firstSeenRank": 3, "firstSeenPrice": 0.00288580446195369, "firstSeenTimestampInSeconds": 1731833701, "rankChange": -3, "firstSeenPricePercentChange": 118.68500149460695, "firstSeenMaxPricePercentageChange": 148.01687986826883}, {"rank": 7, "chainId": "0x1", "coinAddress": "0xb2617246d0c6c0087f18703d576831899ca94f01", "imgURL": "https://d23exngyjlavgo.cloudfront.net/0x1_0xb2617246d0c6c0087f18703d576831899ca94f01", "name": "ZigCoin", "symbol": "ZIG", "uniqueName": "zig-coin", "price": 0.14860954796814935, "price24HChange": 14.960683625833669, "moralisScore": 99, "buyPressure": 62805.477881948005, "twitterFollowerCount": 99207, "volume24H": 1028279.537541074, "categories": ["Platform-Based Utility Tokens"], "blockTimestamp": 1639393819, "fullyDilutedValuation": 248298733.88512588, "hypeScore": 29, "marketCap": 181590357.0606015, "firstSeenRank": 386, "firstSeenPrice": 0.13622182067515468, "firstSeenTimestampInSeconds": 1731949502, "rankChange": 379, "firstSeenPricePercentChange": 9.093790724274216, "firstSeenMaxPricePercentageChange": 11.845701383006736}, {"rank": 8, "chainId": "0x1", "coinAddress": "0x614577036f0a024dbc1c88ba616b394dd65d105a", "imgURL": "https://d23exngyjlavgo.cloudfront.net/0x1_0x614577036f0a024dbc1c88ba616b394dd65d105a", "name": "Genius Token & NFT Collections", "symbol": "GNUS", "uniqueName": "genius-token-nft-collections-1", "price": 6.884246241599577, "price24HChange": 27.80873169681461, "moralisScore": 86, "buyPressure": 103831.08231434003, "twitterFollowerCount": 0, "volume24H": 233925.18235426198, "categories": [], "blockTimestamp": 1708437239, "fullyDilutedValuation": 90398495.57727408, "hypeScore": 28, "marketCap": 4338446.077640134, "firstSeenRank": 37, "firstSeenPrice": 6.325019191174699, "firstSeenTimestampInSeconds": 1731968101, "rankChange": 29, "firstSeenPricePercentChange": 8.84150756736307, "firstSeenMaxPricePercentageChange": 8.84150756736307}, {"rank": 9, "chainId": "0x1", "coinAddress": "0xab814ce69e15f6b9660a3b184c0b0c97b9394a6b", "imgURL": "https://d23exngyjlavgo.cloudfront.net/0x1_0xab814ce69e15f6b9660a3b184c0b0c97b9394a6b", "name": "Cerebrum DAO Token", "symbol": "NEURON", "uniqueName": "cerebrum-dao-token-1", "price": 0.000674614466012255, "price24HChange": 21.873925533818145, "moralisScore": 91, "buyPressure": 140647.40447335396, "twitterFollowerCount": 1938, "volume24H": 245986.68387165404, "categories": ["Platform-Based Utility Tokens"], "blockTimestamp": 1710345227, "fullyDilutedValuation": 54384191.51687634, "hypeScore": 28, "marketCap": 8627742.120103275, "firstSeenRank": 2, "firstSeenPrice": 0.000591256826405097, "firstSeenTimestampInSeconds": 1731866701, "rankChange": -7, "firstSeenPricePercentChange": 14.098380920856524, "firstSeenMaxPricePercentageChange": 14.098380920856524}, {"rank": 10, "chainId": "0x38", "coinAddress": "0x0e09fabb73bd3ade0a17ecc321fd13a19e81ce82", "imgURL": "https://d23exngyjlavgo.cloudfront.net/0x38_0x0e09fabb73bd3ade0a17ecc321fd13a19e81ce82", "name": "PancakeSwap Token", "symbol": "Cake", "uniqueName": "pancake-swap-token-3", "price": 1.9664630246650916, "price24HChange": 5.585022726429436, "moralisScore": 97, "buyPressure": 821114.409245971, "twitterFollowerCount": 1958841, "volume24H": 4895540.674857272, "categories": ["Decentralized Exchange (DEX)"], "blockTimestamp": 1600753666, "fullyDilutedValuation": 673646945.5995916, "hypeScore": 28, "marketCap": 533254882.13825405, "firstSeenRank": 80, "firstSeenPrice": 1.9151053437495298, "firstSeenTimestampInSeconds": 1731940502, "rankChange": 70, "firstSeenPricePercentChange": 2.681715712568066, "firstSeenMaxPricePercentageChange": 2.681715712568066}]}