{"tokens": [{"rank": 1, "chainId": "0x1", "coinAddress": "0x44108f0223a3c3028f5fe7aec7f9bb2e66bef82f", "imgURL": "https://d23exngyjlavgo.cloudfront.net/0x1_0x44108f0223a3c3028f5fe7aec7f9bb2e66bef82f", "name": "Across Protocol Token", "symbol": "ACX", "uniqueName": "across-protocol-token", "price": 0.9993452857927956, "price24HChange": 0.0176060605610569, "moralisScore": 94, "buyPressure": 145329.92605145104, "twitterFollowerCount": 112297, "volume24H": 1850914.5206214513, "categories": ["Layer 2 (L2)", "Platform-Based Utility Tokens"], "blockTimestamp": 1666277435, "fullyDilutedValuation": 1002052300.1591964, "hypeScore": 37, "marketCap": 332970680.20116436, "firstSeenRank": 617, "firstSeenPrice": 0.9967960879017885, "firstSeenTimestampInSeconds": 1733717103, "rankChange": 616, "firstSeenPricePercentChange": 0.2557391548729888, "firstSeenMaxPricePercentageChange": 0.2557391548729888}, {"rank": 2, "chainId": "0x1", "coinAddress": "0x3330bfb7332ca23cd071631837dc289b09c33333", "imgURL": "https://d23exngyjlavgo.cloudfront.net/0x1_0x3330bfb7332ca23cd071631837dc289b09c33333", "name": "RUBIC TOKEN", "symbol": "RBC", "uniqueName": "rubic-token", "price": 0.02803891544452774, "price24HChange": 25.86101415326675, "moralisScore": 97, "buyPressure": 13058.189463087003, "twitterFollowerCount": 221820, "volume24H": 108613.279718425, "categories": ["Cross Chain Communication"], "blockTimestamp": 1670491379, "fullyDilutedValuation": 0, "hypeScore": 36, "marketCap": 0, "firstSeenRank": 11, "firstSeenPrice": 0.028086388678253554, "firstSeenTimestampInSeconds": 1733711102, "rankChange": 9, "firstSeenPricePercentChange": -0.16902576642960454, "firstSeenMaxPricePercentageChange": 0}, {"rank": 3, "chainId": "solana", "coinAddress": "CATTzAwLyADd2ekzVjTjX8tVUBYfrozdkJBkutJggdB7", "imgURL": "https://d23exngyjlavgo.cloudfront.net/solana_CATTzAwLyADd2ekzVjTjX8tVUBYfrozdkJBkutJggdB7", "name": "CatDog", "symbol": "CATDOG", "uniqueName": "cat-dog-20", "price": 2.8081e-05, "price24HChange": 4.51588785046729, "moralisScore": 86, "buyPressure": 9278.319424458, "twitterFollowerCount": 71252, "volume24H": 183440.865311926, "categories": [], "blockTimestamp": 1721528305, "fullyDilutedValuation": 0, "hypeScore": 35, "marketCap": 0, "firstSeenRank": 78, "firstSeenPrice": 2.7958e-05, "firstSeenTimestampInSeconds": 1733716202, "rankChange": 75, "firstSeenPricePercentChange": 0.43994563273482384, "firstSeenMaxPricePercentageChange": 0.43994563273482384}, {"rank": 4, "chainId": "0x1", "coinAddress": "0xa35923162c49cf95e6bf26623385eb431ad920d3", "imgURL": "https://d23exngyjlavgo.cloudfront.net/0x1_0xa35923162c49cf95e6bf26623385eb431ad920d3", "name": "Turbo", "symbol": "TURBO", "uniqueName": "turbo-4", "price": 0.011888771361047528, "price24HChange": 5.839837798201027, "moralisScore": 99, "buyPressure": 270438.83672471903, "twitterFollowerCount": 74351, "volume24H": 2264576.6248107287, "categories": ["Meme", "Platform-Based Utility Tokens"], "blockTimestamp": 1682740679, "fullyDilutedValuation": 777970554.9647955, "hypeScore": 33, "marketCap": 777970554.9647955, "firstSeenRank": 217, "firstSeenPrice": 0.011116799927662636, "firstSeenTimestampInSeconds": 1733695502, "rankChange": 213, "firstSeenPricePercentChange": 6.9441875216621165, "firstSeenMaxPricePercentageChange": 6.9441875216621165}, {"rank": 5, "chainId": "0x2105", "coinAddress": "0x6797b6244fa75f2e78cdffc3a4eb169332b730cc", "imgURL": "https://d23exngyjlavgo.cloudfront.net/0x2105_0x6797b6244fa75f2e78cdffc3a4eb169332b730cc", "name": "Eagle AI", "symbol": "EAI", "uniqueName": "eagle-ai-7", "price": 0.44059614046383583, "price24HChange": 94.10270824461804, "moralisScore": 74, "buyPressure": 137703.112696209, "twitterFollowerCount": 3134, "volume24H": 2572437.9877720173, "categories": [], "blockTimestamp": 1715947905, "fullyDilutedValuation": 0, "hypeScore": 33, "marketCap": 0, "firstSeenRank": 75, "firstSeenPrice": 0.12355526244562708, "firstSeenTimestampInSeconds": 1733375703, "rankChange": 70, "firstSeenPricePercentChange": 256.5984416549872, "firstSeenMaxPricePercentageChange": 256.5984416549872}, {"rank": 6, "chainId": "0x38", "coinAddress": "0x9767c8e438aa18f550208e6d1fdf5f43541cc2c8", "imgURL": "https://d23exngyjlavgo.cloudfront.net/0x38_0x9767c8e438aa18f550208e6d1fdf5f43541cc2c8", "name": "Mango Man Intelligent", "symbol": "MMIT", "uniqueName": "mango-man-intelligent-2", "price": 3.736008636e-09, "price24HChange": 55.254442670305, "moralisScore": 95, "buyPressure": 20295.472049516, "twitterFollowerCount": 37945, "volume24H": 150350.251124996, "categories": ["Meme"], "blockTimestamp": 1652435433, "fullyDilutedValuation": 4879093.607102809, "hypeScore": 32, "marketCap": 708574.0672275067, "firstSeenRank": 5, "firstSeenPrice": 4.130256058e-09, "firstSeenTimestampInSeconds": 1733713202, "rankChange": -1, "firstSeenPricePercentChange": -9.545350614191861, "firstSeenMaxPricePercentageChange": 4.756197660421179}, {"rank": 7, "chainId": "solana", "coinAddress": "A9ZirY82Mk53GNAFjuxNiHUkQLewNvG4hNEHj3EvHfVR", "imgURL": null, "name": "SCOOTERXBT SHITCOIN", "symbol": "SCOOTER", "uniqueName": "scooterxbtshitcoin-1", "price": 0.000841142, "price24HChange": -11.13583251985108, "moralisScore": 67, "buyPressure": -2310.3596346200034, "twitterFollowerCount": 0, "volume24H": 202133.125557772, "categories": [], "blockTimestamp": 1717030001, "fullyDilutedValuation": 838723.7483121974, "hypeScore": 31, "marketCap": 838723.7483121974, "firstSeenRank": 1, "firstSeenPrice": 0.00197043, "firstSeenTimestampInSeconds": 1733666101, "rankChange": -6, "firstSeenPricePercentChange": -57.311754287135294, "firstSeenMaxPricePercentageChange": 13.489948894403762}, {"rank": 8, "chainId": "0x1", "coinAddress": "0x66bff695f3b16a824869a8018a3a6e3685241269", "imgURL": "https://d23exngyjlavgo.cloudfront.net/0x1_0x66bff695f3b16a824869a8018a3a6e3685241269", "name": "Brett", "symbol": "BRETT", "uniqueName": "brett-53", "price": 2.2174393093603e-05, "price24HChange": 21.694210473397096, "moralisScore": 92, "buyPressure": 54528.394641012, "twitterFollowerCount": 1290, "volume24H": 467667.72960800806, "categories": ["Meme"], "blockTimestamp": 1714535435, "fullyDilutedValuation": 23165108.144513287, "hypeScore": 30, "marketCap": 23165108.144513287, "firstSeenRank": 216, "firstSeenPrice": 2.1511142285821e-05, "firstSeenTimestampInSeconds": 1733695502, "rankChange": 208, "firstSeenPricePercentChange": 3.083289576022081, "firstSeenMaxPricePercentageChange": 7.66700297954936}, {"rank": 9, "chainId": "0x2105", "coinAddress": "0xe842e272a18625319cc36f64eb9f97e5ad0c32af", "imgURL": "https://d23exngyjlavgo.cloudfront.net/0x2105_0xe842e272a18625319cc36f64eb9f97e5ad0c32af", "name": "The Blue Dragon", "symbol": "RYU", "uniqueName": "the-blue-dragon-1", "price": 3.85671e-13, "price24HChange": 861.6771394374626, "moralisScore": 79, "buyPressure": 79310.313225741, "twitterFollowerCount": 2831, "volume24H": 254361.928173263, "categories": [], "blockTimestamp": 1712842191, "fullyDilutedValuation": 50229.53853910179, "hypeScore": 30, "marketCap": 50229.53853910179, "firstSeenRank": 1, "firstSeenPrice": 6.17303e-13, "firstSeenTimestampInSeconds": 1733716802, "rankChange": -8, "firstSeenPricePercentChange": -37.52322603324462, "firstSeenMaxPricePercentageChange": 0}, {"rank": 10, "chainId": "0x2105", "coinAddress": "0xcbb7c0000ab88b473b1f5afd9ef808440eed33bf", "imgURL": "https://d23exngyjlavgo.cloudfront.net/0x2105_0xcbb7c0000ab88b473b1f5afd9ef808440eed33bf", "name": "Coinbase Wrapped BTC", "symbol": "cbBTC", "uniqueName": "coinbase-wrapped-btc-1", "price": 99368.89042792708, "price24HChange": -1.0863447858800892, "moralisScore": 67, "buyPressure": 3823801.367620839, "twitterFollowerCount": 0, "volume24H": 210054317.94101682, "categories": [], "blockTimestamp": 1724165533, "fullyDilutedValuation": 426690396.52454156, "hypeScore": 30, "marketCap": 427031868.3409386, "firstSeenRank": 48, "firstSeenPrice": 103389.70628387181, "firstSeenTimestampInSeconds": 1733375703, "rankChange": 38, "firstSeenPricePercentChange": -3.888990500567808, "firstSeenMaxPricePercentageChange": 0.43069591722025535}]}