{"tokens": [{"rank": 1, "chainId": "0x1", "coinAddress": "0xcdb4a8742ed7d0259b51e3454c46c9d6c48d5e88", "imgURL": "https://d23exngyjlavgo.cloudfront.net/0x1_0xcdb4a8742ed7d0259b51e3454c46c9d6c48d5e88", "name": "GPT Protocol", "symbol": "GPT", "uniqueName": "gpt-protocol-2", "price": 0.005140337930313482, "price24HChange": 40.968746358378084, "moralisScore": 92, "buyPressure": 81183.536303796, "twitterFollowerCount": 27331, "volume24H": 120887.988709174, "categories": [], "blockTimestamp": 1705478399, "fullyDilutedValuation": 4047183.9095361144, "hypeScore": 44, "marketCap": 1382612.3863169514, "firstSeenRank": 106, "firstSeenPrice": 0.004848469495661578, "firstSeenTimestampInSeconds": 1733327702, "rankChange": 105, "firstSeenPricePercentChange": 6.019805526528903, "firstSeenMaxPricePercentageChange": 6.019805526528903}, {"rank": 2, "chainId": "0x1", "coinAddress": "0x5485a469faea1492191cfce7528ab6e58135aa4d", "imgURL": "https://d23exngyjlavgo.cloudfront.net/0x1_0x5485a469faea1492191cfce7528ab6e58135aa4d", "name": "Osmi AI", "symbol": "OSMI", "uniqueName": "osmi-ai-1", "price": 0.3228324036045386, "price24HChange": 15.90880579858213, "moralisScore": 79, "buyPressure": 113247.932253277, "twitterFollowerCount": 3126, "volume24H": 200334.97514391705, "categories": ["Platform-Based Utility Tokens", "DePIN"], "blockTimestamp": 1730221919, "fullyDilutedValuation": 30766879.57615593, "hypeScore": 34, "marketCap": 2704941.2755748434, "firstSeenRank": 104, "firstSeenPrice": 0.3167896336290897, "firstSeenTimestampInSeconds": 1733328302, "rankChange": 102, "firstSeenPricePercentChange": 1.9075024350462222, "firstSeenMaxPricePercentageChange": 1.9075024350462222}, {"rank": 3, "chainId": "0x1", "coinAddress": "0x0f2d719407fdbeff09d87557abb7232601fd9f29", "imgURL": "https://d23exngyjlavgo.cloudfront.net/0x1_0x0f2d719407fdbeff09d87557abb7232601fd9f29", "name": "Synapse", "symbol": "SYN", "uniqueName": "synapse", "price": 1.0220906659644424, "price24HChange": 37.64410496889454, "moralisScore": 97, "buyPressure": 444138.103780467, "twitterFollowerCount": 72555, "volume24H": 1922832.3666890028, "categories": ["Interoperability", "Platform-Based Utility Tokens"], "blockTimestamp": 1628972634, "fullyDilutedValuation": 0, "hypeScore": 34, "marketCap": 0, "firstSeenRank": 68, "firstSeenPrice": 0.8521298258566837, "firstSeenTimestampInSeconds": 1733325903, "rankChange": 65, "firstSeenPricePercentChange": 19.94541617374906, "firstSeenMaxPricePercentageChange": 19.94541617374906}, {"rank": 4, "chainId": "0x1", "coinAddress": "0x30d20208d987713f46dfd34ef128bb16c404d10f", "imgURL": "https://d23exngyjlavgo.cloudfront.net/0x1_0x30d20208d987713f46dfd34ef128bb16c404d10f", "name": "Stader", "symbol": "SD", "uniqueName": "stader", "price": 1.1958816859192956, "price24HChange": 23.16961000268798, "moralisScore": 94, "buyPressure": 67233.204600735, "twitterFollowerCount": 101060, "volume24H": 233477.350806211, "categories": ["Platform-Based Utility Tokens", "Exchange-Issued Asset Tokens", "Liquid Staking Tokens"], "blockTimestamp": 1642382811, "fullyDilutedValuation": 0, "hypeScore": 34, "marketCap": 0, "firstSeenRank": 80, "firstSeenPrice": 1.015135647337856, "firstSeenTimestampInSeconds": 1733327102, "rankChange": 76, "firstSeenPricePercentChange": 17.80511196266599, "firstSeenMaxPricePercentageChange": 17.80511196266599}, {"rank": 5, "chainId": "0x1", "coinAddress": "0x50327c6c5a14dcade707abad2e27eb517df87ab5", "imgURL": "https://d23exngyjlavgo.cloudfront.net/0x1_0x50327c6c5a14dcade707abad2e27eb517df87ab5", "name": "TRON", "symbol": "TRX", "uniqueName": "tron-4", "price": 0.33946217531609874, "price24HChange": 22.705827912481727, "moralisScore": 97, "buyPressure": 289627.373216973, "twitterFollowerCount": 1570660, "volume24H": 1636172.9015590409, "categories": ["Platform-Based Utility Tokens"], "blockTimestamp": 1644831031, "fullyDilutedValuation": 55450608.0077054, "hypeScore": 33, "marketCap": 55450608.0077054, "firstSeenRank": 83, "firstSeenPrice": 0.3789216455353324, "firstSeenTimestampInSeconds": 1733316903, "rankChange": 78, "firstSeenPricePercentChange": -10.413622627307602, "firstSeenMaxPricePercentageChange": 1.0738655839984799}, {"rank": 6, "chainId": "0x38", "coinAddress": "0x9f589e3eabe42ebc94a44727b3f3531c0c877809", "imgURL": "https://d23exngyjlavgo.cloudfront.net/0x38_0x9f589e3eabe42ebc94a44727b3f3531c0c877809", "name": "Tokocrypto Token", "symbol": "TKO", "uniqueName": "tokocrypto-token", "price": 0.4986376890230231, "price24HChange": 14.779020325014068, "moralisScore": 97, "buyPressure": 4265.236105090999, "twitterFollowerCount": 357730, "volume24H": 161970.64541761702, "categories": ["Decentralized Exchange (DEX)", "Platform-Based Utility Tokens", "Stablecoins"], "blockTimestamp": 1617298250, "fullyDilutedValuation": 251748942.75880635, "hypeScore": 33, "marketCap": 85646236.8837758, "firstSeenRank": 441, "firstSeenPrice": 0.503485346156096, "firstSeenTimestampInSeconds": 1733305503, "rankChange": 435, "firstSeenPricePercentChange": -0.9628199053026596, "firstSeenMaxPricePercentageChange": 2.115800003020136}, {"rank": 7, "chainId": "0xa4b1", "coinAddress": "0x13a7dedb7169a17be92b0e3c7c2315b46f4772b3", "imgURL": "https://d23exngyjlavgo.cloudfront.net/0xa4b1_0x13a7dedb7169a17be92b0e3c7c2315b46f4772b3", "name": "Boop", "symbol": "Boop", "uniqueName": "boop-1", "price": 0.00018093273547167, "price24HChange": 34.04530814538733, "moralisScore": 92, "buyPressure": 69692.933932861, "twitterFollowerCount": 4995, "volume24H": 309135.82050001906, "categories": [], "blockTimestamp": 1702958123, "fullyDilutedValuation": 0, "hypeScore": 33, "marketCap": 0, "firstSeenRank": 350, "firstSeenPrice": 0.000147392438044991, "firstSeenTimestampInSeconds": 1733288102, "rankChange": 343, "firstSeenPricePercentChange": 22.755778974523064, "firstSeenMaxPricePercentageChange": 22.755778974523064}, {"rank": 8, "chainId": "0xa4b1", "coinAddress": "0x58b9cb810a68a7f3e1e4f8cb45d1b9b3c79705e8", "imgURL": "https://d23exngyjlavgo.cloudfront.net/0xa4b1_0x58b9cb810a68a7f3e1e4f8cb45d1b9b3c79705e8", "name": "Connext", "symbol": "NEXT", "uniqueName": "connext", "price": 0.13682362625577102, "price24HChange": 11.126036819401415, "moralisScore": 91, "buyPressure": 13525.289833394996, "twitterFollowerCount": 40, "volume24H": 138648.35967406703, "categories": [], "blockTimestamp": 1693777932, "fullyDilutedValuation": 3682421.0351873427, "hypeScore": 33, "marketCap": 3682421.0351873427, "firstSeenRank": 9, "firstSeenPrice": 0.13673519232021697, "firstSeenTimestampInSeconds": 1733311202, "rankChange": 1, "firstSeenPricePercentChange": 0.06467532904546504, "firstSeenMaxPricePercentageChange": 3.8172151045909803}, {"rank": 9, "chainId": "0x38", "coinAddress": "0x0f1cbed8efa0e012adbccb1638d0ab0147d5ac00", "imgURL": "https://d23exngyjlavgo.cloudfront.net/0x38_0x0f1cbed8efa0e012adbccb1638d0ab0147d5ac00", "name": "HELLO", "symbol": "HELLO", "uniqueName": "hello-8", "price": 0.0288805626716122, "price24HChange": 39.37978371485617, "moralisScore": 96, "buyPressure": 138121.43739491698, "twitterFollowerCount": 83135, "volume24H": 599236.048074673, "categories": ["NFT", "Gaming (GameFi)"], "blockTimestamp": 1665568703, "fullyDilutedValuation": 27153312.59759972, "hypeScore": 32, "marketCap": 17133044.80331452, "firstSeenRank": 162, "firstSeenPrice": 0.02703001613934637, "firstSeenTimestampInSeconds": 1733303103, "rankChange": 153, "firstSeenPricePercentChange": 6.846264991947488, "firstSeenMaxPricePercentageChange": 8.46532960895908}, {"rank": 10, "chainId": "0x1", "coinAddress": "0x728f30fa2f100742c7949d1961804fa8e0b1387d", "imgURL": "https://d23exngyjlavgo.cloudfront.net/0x1_0x728f30fa2f100742c7949d1961804fa8e0b1387d", "name": "GamerCoin", "symbol": "GHX", "uniqueName": "gamer-coin", "price": 0.11027353995545483, "price24HChange": 19.202646492221408, "moralisScore": 99, "buyPressure": 22570.500218261997, "twitterFollowerCount": 90700, "volume24H": 286653.18795714, "categories": ["Platform-Based Utility Tokens", "Play To Earn"], "blockTimestamp": 1607626946, "fullyDilutedValuation": 0, "hypeScore": 31, "marketCap": 0, "firstSeenRank": 95, "firstSeenPrice": 0.1050315420867277, "firstSeenTimestampInSeconds": 1733313302, "rankChange": 85, "firstSeenPricePercentChange": 4.9908796582255786, "firstSeenMaxPricePercentageChange": 9.022276849132194}]}