{"tokens": [{"rank": 1, "chainId": "0xa4b1", "coinAddress": "0xeb466342c4d449bc9f53a865d5cb90586f405215", "imgURL": "https://d23exngyjlavgo.cloudfront.net/0xa4b1_0xeb466342c4d449bc9f53a865d5cb90586f405215", "name": "Axelar Wrapped USDC", "symbol": "axlUSDC", "uniqueName": "axelar-wrapped-usdc", "price": 1.0004282858556561, "price24HChange": 0.0593520407896577, "moralisScore": 95, "buyPressure": 33515.116460351004, "twitterFollowerCount": 878, "volume24H": 370184.5898523929, "categories": ["Interoperability"], "blockTimestamp": 1670276939, "fullyDilutedValuation": 515511.42497650225, "hypeScore": 36, "marketCap": 515511.42497650225, "firstSeenRank": 3, "firstSeenPrice": 0.9998356255017583, "firstSeenTimestampInSeconds": 1731816901, "rankChange": 2, "firstSeenPricePercentChange": 0.05927577881618306, "firstSeenMaxPricePercentageChange": 0.05927577881618306}, {"rank": 2, "chainId": "0xfa", "coinAddress": "0x662b3d319e693aa578edd4bd8a5c9395bc49e9f4", "imgURL": "https://d23exngyjlavgo.cloudfront.net/0xfa_0x662b3d319e693aa578edd4bd8a5c9395bc49e9f4", "name": "GOGGLES", "symbol": "GOGLZ", "uniqueName": "goggles-2", "price": 0.5404877619742479, "price24HChange": 15.80002703065752, "moralisScore": 85, "buyPressure": 67407.03546704604, "twitterFollowerCount": 1792, "volume24H": 3997983.965134204, "categories": [], "blockTimestamp": 1727888111, "fullyDilutedValuation": 17773307.268213674, "hypeScore": 34, "marketCap": 17773307.268213674, "firstSeenRank": 101, "firstSeenPrice": 0.49211962820306404, "firstSeenTimestampInSeconds": 1731780902, "rankChange": 99, "firstSeenPricePercentChange": 9.828531722621234, "firstSeenMaxPricePercentageChange": 27.871707821739307}, {"rank": 3, "chainId": "0x89", "coinAddress": "0xd0258a3fd00f38aa8090dfee343f10a9d4d30d3f", "imgURL": "https://d23exngyjlavgo.cloudfront.net/0x89_0xd0258a3fd00f38aa8090dfee343f10a9d4d30d3f", "name": "VOXEL Token", "symbol": "VOXEL", "uniqueName": "voxel-token", "price": 0.17253346292582453, "price24HChange": 7.175371977650686, "moralisScore": 98, "buyPressure": 288798.60247722705, "twitterFollowerCount": 71243, "volume24H": 2000455.893461305, "categories": ["Platform-Based Utility Tokens"], "blockTimestamp": 1638678009, "fullyDilutedValuation": 49748233.55726732, "hypeScore": 32, "marketCap": 34862871.31134522, "firstSeenRank": 140, "firstSeenPrice": 0.15649915440340476, "firstSeenTimestampInSeconds": 1731699901, "rankChange": 137, "firstSeenPricePercentChange": 10.24561990992517, "firstSeenMaxPricePercentageChange": 10.859939344969176}, {"rank": 4, "chainId": "0x1", "coinAddress": "0x9fd9278f04f01c6a39a9d1c1cd79f7782c6ade08", "imgURL": "https://d23exngyjlavgo.cloudfront.net/0x1_0x9fd9278f04f01c6a39a9d1c1cd79f7782c6ade08", "name": "Biaoqing", "symbol": "BIAO", "uniqueName": "biaoqing-11", "price": 0.001965681237671505, "price24HChange": 20.492153370291454, "moralisScore": 86, "buyPressure": 22546.634823118, "twitterFollowerCount": 11785, "volume24H": 196855.05770202397, "categories": ["Meme"], "blockTimestamp": 1717880327, "fullyDilutedValuation": 1828101.6368515722, "hypeScore": 29, "marketCap": 1828101.6368515722, "firstSeenRank": 48, "firstSeenPrice": 0.002031748665712048, "firstSeenTimestampInSeconds": 1731750301, "rankChange": 44, "firstSeenPricePercentChange": -3.251752008282433, "firstSeenMaxPricePercentageChange": 25.040999326255616}, {"rank": 5, "chainId": "solana", "coinAddress": "EYrci5wDqErWHXjKPLxeWtbXq36JcFKzCC7JoMi1pump", "imgURL": "https://d23exngyjlavgo.cloudfront.net/solana_EYrci5wDqErWHXjKPLxeWtbXq36JcFKzCC7JoMi1pump", "name": "Singularity's Child gonzo/ai", "symbol": "Child AI", "uniqueName": "singularitys-childgonzoai-1", "price": 0.000855371, "price24HChange": 45.29883825251281, "moralisScore": 66, "buyPressure": 18810.364354000998, "twitterFollowerCount": 0, "volume24H": 129077.003596043, "categories": [], "blockTimestamp": 1728957897, "fullyDilutedValuation": 529548.0048215014, "hypeScore": 29, "marketCap": 529548.0048215014, "firstSeenRank": 22, "firstSeenPrice": 0.00076364, "firstSeenTimestampInSeconds": 1731832501, "rankChange": 17, "firstSeenPricePercentChange": 12.012335655544492, "firstSeenMaxPricePercentageChange": 12.012335655544492}, {"rank": 6, "chainId": "solana", "coinAddress": "Be6a7UZT4k6yUgQibJczPat8C2qGujEAoje7wY7Pgegr", "imgURL": "https://d23exngyjlavgo.cloudfront.net/solana_Be6a7UZT4k6yUgQibJczPat8C2qGujEAoje7wY7Pgegr", "name": "Blackcroc", "symbol": "blackcroc", "uniqueName": "blackcroc-1", "price": 0.000219088, "price24HChange": 36.20470991967772, "moralisScore": 81, "buyPressure": 3942.420475117001, "twitterFollowerCount": 0, "volume24H": 126789.57192503501, "categories": ["Meme"], "blockTimestamp": 1711310545, "fullyDilutedValuation": 172534.06631069805, "hypeScore": 27, "marketCap": 172534.06631069805, "firstSeenRank": 296, "firstSeenPrice": 0.00017384, "firstSeenTimestampInSeconds": 1731774901, "rankChange": 290, "firstSeenPricePercentChange": 26.028531983433034, "firstSeenMaxPricePercentageChange": 27.685227795674187}, {"rank": 7, "chainId": "0x1", "coinAddress": "0x3472a5a71965499acd81997a54bba8d852c6e53d", "imgURL": "https://d23exngyjlavgo.cloudfront.net/0x1_0x3472a5a71965499acd81997a54bba8d852c6e53d", "name": "Badger", "symbol": "BADGER", "uniqueName": "badger-2", "price": 3.198784969754066, "price24HChange": 3.96930711785379, "moralisScore": 66, "buyPressure": 234169.052909937, "twitterFollowerCount": 50593, "volume24H": 702648.5585966329, "categories": ["Yield Farming", "Platform-Based Utility Tokens"], "blockTimestamp": 1606584709, "fullyDilutedValuation": 69419292.2001622, "hypeScore": 26, "marketCap": 67075868.207034595, "firstSeenRank": 363, "firstSeenPrice": 3.2820765608150655, "firstSeenTimestampInSeconds": 1731794701, "rankChange": 356, "firstSeenPricePercentChange": -2.5377711189136676, "firstSeenMaxPricePercentageChange": 0.12094073416597936}, {"rank": 8, "chainId": "0x1", "coinAddress": "0xec67005c4e498ec7f55e092bd1d35cbc47c91892", "imgURL": "https://d23exngyjlavgo.cloudfront.net/0x1_0xec67005c4e498ec7f55e092bd1d35cbc47c91892", "name": "Melon Token", "symbol": "MLN", "uniqueName": "melon-token", "price": 15.759195022175422, "price24HChange": 4.995004415027531, "moralisScore": 97, "buyPressure": 9727.485500541, "twitterFollowerCount": 35951, "volume24H": 152834.41033242698, "categories": ["Asset-backed Tokens", "Decentralized Finance (DeFi)"], "blockTimestamp": 1548528955, "fullyDilutedValuation": 32587590.22538932, "hypeScore": 26, "marketCap": 32587590.22538932, "firstSeenRank": 24, "firstSeenPrice": 15.81497673833942, "firstSeenTimestampInSeconds": 1731782701, "rankChange": 16, "firstSeenPricePercentChange": -0.35271450022919343, "firstSeenMaxPricePercentageChange": 2.2388511425528344}, {"rank": 9, "chainId": "0x38", "coinAddress": "0x3203c9e46ca618c8c1ce5dc67e7e9d75f5da2377", "imgURL": "https://d23exngyjlavgo.cloudfront.net/0x38_0x3203c9e46ca618c8c1ce5dc67e7e9d75f5da2377", "name": "Mobox", "symbol": "MBOX", "uniqueName": "mobox", "price": 0.2136665023274432, "price24HChange": 13.652966757385592, "moralisScore": 97, "buyPressure": 236710.108638574, "twitterFollowerCount": 379341, "volume24H": 1764162.8582550199, "categories": ["Platform-Based Utility Tokens"], "blockTimestamp": 1617348421, "fullyDilutedValuation": 88927309.69583587, "hypeScore": 26, "marketCap": 74120935.02239883, "firstSeenRank": 403, "firstSeenPrice": 0.18157840748038231, "firstSeenTimestampInSeconds": 1731812701, "rankChange": 394, "firstSeenPricePercentChange": 17.671756951898406, "firstSeenMaxPricePercentageChange": 17.671756951898406}, {"rank": 10, "chainId": "0x1", "coinAddress": "0x30d20208d987713f46dfd34ef128bb16c404d10f", "imgURL": "https://d23exngyjlavgo.cloudfront.net/0x1_0x30d20208d987713f46dfd34ef128bb16c404d10f", "name": "Stader", "symbol": "SD", "uniqueName": "stader", "price": 1.1823110979171685, "price24HChange": 66.88615398779297, "moralisScore": 94, "buyPressure": 484660.7758189541, "twitterFollowerCount": 101060, "volume24H": 1608901.752613228, "categories": ["Platform-Based Utility Tokens", "Exchange-Issued Asset Tokens", "Liquid Staking Tokens"], "blockTimestamp": 1642382811, "fullyDilutedValuation": 122602558.48262946, "hypeScore": 24, "marketCap": 33317751.466534022, "firstSeenRank": 132, "firstSeenPrice": 0.7718165229530461, "firstSeenTimestampInSeconds": 1731776701, "rankChange": 122, "firstSeenPricePercentChange": 53.185512716614255, "firstSeenMaxPricePercentageChange": 81.7402773489594}]}