{"tokens": [{"rank": 1, "chainId": "0x2105", "coinAddress": "0x2d7b9847d5a8baa516c889f366452160dc4a7b04", "imgURL": null, "name": "catwifhat", "symbol": "cif", "uniqueName": "catwifhat-1", "price": 5.73796055391e-07, "price24HChange": 268.5787428495475, "moralisScore": 72, "buyPressure": 45017.820320363, "twitterFollowerCount": 0, "volume24H": 113357.492871583, "categories": [], "blockTimestamp": 1702740745, "fullyDilutedValuation": 343792.51673035714, "hypeScore": 38, "marketCap": 343055.62700048625, "firstSeenRank": 38, "firstSeenPrice": 6.20494839724e-07, "firstSeenTimestampInSeconds": 1735836301, "rankChange": 37, "firstSeenPricePercentChange": -7.526055229366911, "firstSeenMaxPricePercentageChange": 0}, {"rank": 2, "chainId": "0x1", "coinAddress": "0xdd66781d0e9a08d4fbb5ec7bac80b691be27f21d", "imgURL": "https://adds-token-info-29a861f.s3.amazonaws.com/0x1/0xdd66781d0e9a08d4fbb5ec7bac80b691be27f21d/logo.jpg", "name": "AxonDAO Governance Token", "symbol": "AXGT", "uniqueName": "axon-dao-governance-token-1", "price": 0.3125336544654041, "price24HChange": 20.603365663376277, "moralisScore": 97, "buyPressure": 100364.13113377901, "twitterFollowerCount": 17167, "volume24H": 235369.204391551, "categories": [], "blockTimestamp": 1697894807, "fullyDilutedValuation": 291348336.429171, "hypeScore": 37, "marketCap": 52801275.48287263, "firstSeenRank": 359, "firstSeenPrice": 0.2913970925646131, "firstSeenTimestampInSeconds": 1735841101, "rankChange": 357, "firstSeenPricePercentChange": 7.253525323388142, "firstSeenMaxPricePercentageChange": 7.253525323388142}, {"rank": 3, "chainId": "0x1", "coinAddress": "0xc06caead870d3a8af2504637b6c5b7248bed6116", "imgURL": "https://d23exngyjlavgo.cloudfront.net/0x1_0xc06caead870d3a8af2504637b6c5b7248bed6116", "name": "Business Coin", "symbol": "BUSINESS", "uniqueName": "business-coin", "price": 0.009070491390526606, "price24HChange": 66.8505041258248, "moralisScore": 92, "buyPressure": 42479.75091919501, "twitterFollowerCount": 962, "volume24H": 105721.692434891, "categories": [], "blockTimestamp": 1695169343, "fullyDilutedValuation": 5371800.882560491, "hypeScore": 37, "marketCap": 5371800.882560491, "firstSeenRank": 3, "firstSeenPrice": 0.009070491390526606, "firstSeenTimestampInSeconds": 1735857301, "rankChange": 0, "firstSeenPricePercentChange": 0, "firstSeenMaxPricePercentageChange": 0}, {"rank": 4, "chainId": "0xa86a", "coinAddress": "0x79ea4e536f598dcd67c76ee3829f84ab9e72a558", "imgURL": "https://d23exngyjlavgo.cloudfront.net/0xa86a_0x79ea4e536f598dcd67c76ee3829f84ab9e72a558", "name": "ai9000 Token", "symbol": "AI9000", "uniqueName": "ai-9000-token-1", "price": 0.015124155163385024, "price24HChange": 60.051266680968205, "moralisScore": 83, "buyPressure": 114215.750603343, "twitterFollowerCount": 1193, "volume24H": 335416.2992054509, "categories": [], "blockTimestamp": 1733932887, "fullyDilutedValuation": 11386698.444849448, "hypeScore": 35, "marketCap": 11386698.444849448, "firstSeenRank": 31, "firstSeenPrice": 0.011967300940020105, "firstSeenTimestampInSeconds": 1735830002, "rankChange": 27, "firstSeenPricePercentChange": 26.378999234556023, "firstSeenMaxPricePercentageChange": 26.378999234556023}, {"rank": 5, "chainId": "0x1", "coinAddress": "0x9343e24716659a3551eb10aff9472a2dcad5db2d", "imgURL": "https://d23exngyjlavgo.cloudfront.net/0x1_0x9343e24716659a3551eb10aff9472a2dcad5db2d", "name": "STFX", "symbol": "STFX", "uniqueName": "stfx", "price": 0.010638933339860069, "price24HChange": 26.375626991990288, "moralisScore": 96, "buyPressure": 56605.15742017799, "twitterFollowerCount": 36189, "volume24H": 273345.699824592, "categories": ["Platform-Based Utility Tokens", "Decentralized Perpetuals"], "blockTimestamp": 1674341375, "fullyDilutedValuation": 8138266.707060782, "hypeScore": 33, "marketCap": 5947730.398001236, "firstSeenRank": 148, "firstSeenPrice": 0.009347195123022336, "firstSeenTimestampInSeconds": 1735850701, "rankChange": 143, "firstSeenPricePercentChange": 13.819527674736932, "firstSeenMaxPricePercentageChange": 26.52727026644368}, {"rank": 6, "chainId": "solana", "coinAddress": "GVwpWU5PtJFHS1mH35sHmsRN1XWUwRV3Qo94h5Lepump", "imgURL": "https://d23exngyjlavgo.cloudfront.net/solana_GVwpWU5PtJFHS1mH35sHmsRN1XWUwRV3Qo94h5Lepump", "name": "cat girl", "symbol": "CATGF", "uniqueName": "catgirl-14", "price": 0.001444014, "price24HChange": 241.028524790066, "moralisScore": 80, "buyPressure": 37239.41720475699, "twitterFollowerCount": 0, "volume24H": 653527.2937595149, "categories": ["Meme", "Pump.fun"], "blockTimestamp": 1729280357, "fullyDilutedValuation": 352731.58993710816, "hypeScore": 33, "marketCap": 352731.58993710816, "firstSeenRank": 48, "firstSeenPrice": 0.000936141, "firstSeenTimestampInSeconds": 1735819503, "rankChange": 42, "firstSeenPricePercentChange": 54.251763356161085, "firstSeenMaxPricePercentageChange": 54.251763356161085}, {"rank": 7, "chainId": "solana", "coinAddress": "HH8bchogQD71iuLghP4cuvSU7vsGJoMJDBxvWTFu7MpA", "imgURL": "https://d23exngyjlavgo.cloudfront.net/solana_HH8bchogQD71iuLghP4cuvSU7vsGJoMJDBxvWTFu7MpA", "name": "UCIT", "symbol": "UCIT", "uniqueName": "ucit-1", "price": 7.44437e-08, "price24HChange": 1272579896.7779965, "moralisScore": 78, "buyPressure": 1118.626677695288, "twitterFollowerCount": 1638, "volume24H": 1337005919.898112, "categories": ["Meme"], "blockTimestamp": 1710561922, "fullyDilutedValuation": 65080.786506227756, "hypeScore": 33, "marketCap": 65080.786506227756, "firstSeenRank": 2, "firstSeenPrice": 7.50374e-08, "firstSeenTimestampInSeconds": 1735853101, "rankChange": -5, "firstSeenPricePercentChange": -0.7912054522144898, "firstSeenMaxPricePercentageChange": 1382689065.6693861}, {"rank": 8, "chainId": "0x1", "coinAddress": "0x49fb8ad7578148e17c3ef0c344ce23a66ed372c4", "imgURL": "https://d23exngyjlavgo.cloudfront.net/0x1_0x49fb8ad7578148e17c3ef0c344ce23a66ed372c4", "name": "tao.bot", "symbol": "TAOBOT", "uniqueName": "taobot-1", "price": 0.4875499875866123, "price24HChange": 102.22996493756575, "moralisScore": 67, "buyPressure": 188079.01529203902, "twitterFollowerCount": 2873, "volume24H": 897323.4579449509, "categories": [], "blockTimestamp": 1709755619, "fullyDilutedValuation": 38264006.0403221, "hypeScore": 31, "marketCap": 26784804.22822547, "firstSeenRank": 573, "firstSeenPrice": 0.36825604354169694, "firstSeenTimestampInSeconds": 1735818903, "rankChange": 565, "firstSeenPricePercentChange": 32.39429362722947, "firstSeenMaxPricePercentageChange": 39.2191587752655}, {"rank": 9, "chainId": "0x1", "coinAddress": "0x3ea30722d895d530d63a3fefdfda6fb351594c67", "imgURL": "https://d23exngyjlavgo.cloudfront.net/0x1_0x3ea30722d895d530d63a3fefdfda6fb351594c67", "name": "Bakkt Holdings, Inc.", "symbol": "BKKT", "uniqueName": "bakkt-holdings-inc-1", "price": 0.000235120850492023, "price24HChange": 361.5135964260594, "moralisScore": 71, "buyPressure": 32636.513054945997, "twitterFollowerCount": 303, "volume24H": 140257.860271736, "categories": [], "blockTimestamp": 1731961991, "fullyDilutedValuation": 66566.95629529346, "hypeScore": 30, "marketCap": 66566.95629529346, "firstSeenRank": 11, "firstSeenPrice": 0.00030651176325245, "firstSeenTimestampInSeconds": 1735856701, "rankChange": 2, "firstSeenPricePercentChange": -23.29141041860368, "firstSeenMaxPricePercentageChange": 0}, {"rank": 10, "chainId": "solana", "coinAddress": "wo1zgt8rfrYpvdVi4nidoj1SYfcR4pQx69bmNv2JLhQ", "imgURL": "https://d23exngyjlavgo.cloudfront.net/solana_wo1zgt8rfrYpvdVi4nidoj1SYfcR4pQx69bmNv2JLhQ", "name": "JustAnEgg", "symbol": "EGG", "uniqueName": "just-an-egg-1", "price": 0.001534824, "price24HChange": 34.568421899977864, "moralisScore": 92, "buyPressure": 16485.987646494996, "twitterFollowerCount": 19339, "volume24H": 101143.115391363, "categories": ["Meme"], "blockTimestamp": 1711749749, "fullyDilutedValuation": 614947.2478984664, "hypeScore": 30, "marketCap": 614947.2478984664, "firstSeenRank": 169, "firstSeenPrice": 0.001572304, "firstSeenTimestampInSeconds": 1735847101, "rankChange": 159, "firstSeenPricePercentChange": -2.383762936429603, "firstSeenMaxPricePercentageChange": 0.40825438337623715}]}