{"tokens": [{"rank": 1, "chainId": "solana", "coinAddress": "8NH3AfwkizHmbVd83SSxc2YbsFmFL4m2BeepvL6upump", "imgURL": "https://d23exngyjlavgo.cloudfront.net/solana_8NH3AfwkizHmbVd83SSxc2YbsFmFL4m2BeepvL6upump", "name": "TOP G", "symbol": "TOPG", "uniqueName": "topg-1", "price": 0.000873265, "price24HChange": 106.09628596445269, "moralisScore": 92, "buyPressure": 34969.71244927502, "twitterFollowerCount": 1425, "volume24H": 195164.68462782708, "categories": ["Pump.fun", "Meme"], "blockTimestamp": 1717766698, "fullyDilutedValuation": 190025.29634589978, "hypeScore": 41, "marketCap": 190025.29634589978, "firstSeenRank": 4, "firstSeenPrice": 0.000653771, "firstSeenTimestampInSeconds": 1737255301, "rankChange": 3, "firstSeenPricePercentChange": 33.573529569222245, "firstSeenMaxPricePercentageChange": 33.573529569222245}, {"rank": 2, "chainId": "0x1", "coinAddress": "0x69420e3a3aa9e17dea102bb3a9b3b73dcddb9528", "imgURL": "https://d23exngyjlavgo.cloudfront.net/0x1_0x69420e3a3aa9e17dea102bb3a9b3b73dcddb9528", "name": "Elon", "symbol": "ELON", "uniqueName": "elon-40", "price": 4.690144219262e-06, "price24HChange": 15.879909539126045, "moralisScore": 84, "buyPressure": 54437.10506076299, "twitterFollowerCount": 18627, "volume24H": 191976.800947105, "categories": ["Meme"], "blockTimestamp": 1713942107, "fullyDilutedValuation": 2045100.5605563167, "hypeScore": 35, "marketCap": 2045100.5605563167, "firstSeenRank": 132, "firstSeenPrice": 3.71015475662e-06, "firstSeenTimestampInSeconds": 1737248701, "rankChange": 130, "firstSeenPricePercentChange": 26.41370850888126, "firstSeenMaxPricePercentageChange": 26.41370850888126}, {"rank": 3, "chainId": "solana", "coinAddress": "LX2mJPsutHkUc6iXNFgumSC6LVKyc66xpy2zDTZpump", "imgURL": "https://d23exngyjlavgo.cloudfront.net/solana_LX2mJPsutHkUc6iXNFgumSC6LVKyc66xpy2zDTZpump", "name": "Tate Terminal", "symbol": "Tate", "uniqueName": "tate-terminal-16", "price": 0.002265998, "price24HChange": 5.680038722886467, "moralisScore": 85, "buyPressure": 8069.245651125002, "twitterFollowerCount": 28520, "volume24H": 321109.38216477894, "categories": ["Meme", "Pump.fun"], "blockTimestamp": 1729779247, "fullyDilutedValuation": 1536652.8384619036, "hypeScore": 35, "marketCap": 1536652.8384619036, "firstSeenRank": 3, "firstSeenPrice": 0.002265998, "firstSeenTimestampInSeconds": 1737256501, "rankChange": 0, "firstSeenPricePercentChange": 0, "firstSeenMaxPricePercentageChange": 0}, {"rank": 4, "chainId": "solana", "coinAddress": "3TNvKtqnHJMXD8y5F3rcheZpkC2M1nzJK7csW8jB6MP2", "imgURL": "https://d23exngyjlavgo.cloudfront.net/solana_3TNvKtqnHJMXD8y5F3rcheZpkC2M1nzJK7csW8jB6MP2", "name": "Rooty", "symbol": "Rooty", "uniqueName": "rooty-1", "price": 0.357808269, "price24HChange": -19.716479398127145, "moralisScore": 67, "buyPressure": -52478.8093162, "twitterFollowerCount": 0, "volume24H": 214870.047978714, "categories": [], "blockTimestamp": 1735544776, "fullyDilutedValuation": 337174927.7723988, "hypeScore": 33, "marketCap": 337174927.7723988, "firstSeenRank": 4, "firstSeenPrice": 0.352994292, "firstSeenTimestampInSeconds": 1737249901, "rankChange": 0, "firstSeenPricePercentChange": 1.3637549130681197, "firstSeenMaxPricePercentageChange": 1.3637549130681197}, {"rank": 5, "chainId": "0x1", "coinAddress": "0x81db1949d0e888557bc632f7c0f6698b1f8c9106", "imgURL": "https://d23exngyjlavgo.cloudfront.net/0x1_0x81db1949d0e888557bc632f7c0f6698b1f8c9106", "name": "d/acc", "symbol": "D/ACC", "uniqueName": "dacc-2", "price": 5.2297818592072e-05, "price24HChange": 4.473230710641574, "moralisScore": 99, "buyPressure": 9457.186720612, "twitterFollowerCount": 1626, "volume24H": 159839.606591202, "categories": ["Meme"], "blockTimestamp": 1701120971, "fullyDilutedValuation": 518511.67381329805, "hypeScore": 31, "marketCap": 518511.67381329805, "firstSeenRank": 6, "firstSeenPrice": 5.8605636045383e-05, "firstSeenTimestampInSeconds": 1737246301, "rankChange": 1, "firstSeenPricePercentChange": -10.76315842460332, "firstSeenMaxPricePercentageChange": 0}, {"rank": 6, "chainId": "0x1", "coinAddress": "0x8c7ac134ed985367eadc6f727d79e8295e11435c", "imgURL": "https://d23exngyjlavgo.cloudfront.net/0x1_0x8c7ac134ed985367eadc6f727d79e8295e11435c", "name": "The Balkan Dwarf", "symbol": "Kekec", "uniqueName": "the-balkan-dwarf", "price": 0.000241763339399281, "price24HChange": -1.6450231617898186, "moralisScore": 90, "buyPressure": 4147.391718235007, "twitterFollowerCount": 5676, "volume24H": 205703.92769377297, "categories": [], "blockTimestamp": 1698433607, "fullyDilutedValuation": 9101409.121026082, "hypeScore": 30, "marketCap": 9101409.121026082, "firstSeenRank": 206, "firstSeenPrice": 0.000223732951061981, "firstSeenTimestampInSeconds": 1737253501, "rankChange": 200, "firstSeenPricePercentChange": 8.058888175262577, "firstSeenMaxPricePercentageChange": 8.058888175262577}, {"rank": 7, "chainId": "solana", "coinAddress": "43N5UGr3mnfhJFzpBPNM7ZdnobghiYBtHTaQfZQv65mh", "imgURL": "https://d23exngyjlavgo.cloudfront.net/solana_43N5UGr3mnfhJFzpBPNM7ZdnobghiYBtHTaQfZQv65mh", "name": "MILEI", "symbol": "MILEI", "uniqueName": "milei-1", "price": 0.000215374, "price24HChange": 360.49604447295275, "moralisScore": 81, "buyPressure": 12158.018072024004, "twitterFollowerCount": 1732, "volume24H": 122503.115555828, "categories": [], "blockTimestamp": 1713939082, "fullyDilutedValuation": 167982.0215274107, "hypeScore": 30, "marketCap": 167982.0215274107, "firstSeenRank": 39, "firstSeenPrice": 0.000182026, "firstSeenTimestampInSeconds": 1737251100, "rankChange": 32, "firstSeenPricePercentChange": 18.32045971454627, "firstSeenMaxPricePercentageChange": 18.32045971454627}, {"rank": 8, "chainId": "solana", "coinAddress": "HhCEqzWYMNJskCUM5RPppe6BfxnoWCfHMu7KiAyg7kQZ", "imgURL": "https://d23exngyjlavgo.cloudfront.net/solana_HhCEqzWYMNJskCUM5RPppe6BfxnoWCfHMu7KiAyg7kQZ", "name": "TrumpMeme", "symbol": "TrumpMeme", "uniqueName": "trump-meme-24", "price": 3.2603e-09, "price24HChange": 0, "moralisScore": 82, "buyPressure": -9544.131022420886, "twitterFollowerCount": 0, "volume24H": 4517457.083502531, "categories": [], "blockTimestamp": null, "fullyDilutedValuation": 657.3156487864965, "hypeScore": 27, "marketCap": 657.3156487864965, "firstSeenRank": 311, "firstSeenPrice": 2.3103e-09, "firstSeenTimestampInSeconds": 1737248701, "rankChange": 303, "firstSeenPricePercentChange": 41.120200839717775, "firstSeenMaxPricePercentageChange": 41.120200839717775}, {"rank": 9, "chainId": "solana", "coinAddress": "2vFYpCh2yJhHphft1Z4XHdafEhj6XksyhFyH9tvTdKqf", "imgURL": "https://d23exngyjlavgo.cloudfront.net/solana_2vFYpCh2yJhHphft1Z4XHdafEhj6XksyhFyH9tvTdKqf", "name": "Let's Get This Bread", "symbol": "LGTB", "uniqueName": "lets-get-this-bread-2", "price": 0.000344993, "price24HChange": 23.23379174852652, "moralisScore": 84, "buyPressure": 10950.427420863998, "twitterFollowerCount": 1807, "volume24H": 136690.25238298398, "categories": [], "blockTimestamp": 1733943834, "fullyDilutedValuation": 3102879.932841631, "hypeScore": 27, "marketCap": 3102879.932841631, "firstSeenRank": 126, "firstSeenPrice": 0.000311784, "firstSeenTimestampInSeconds": 1737242701, "rankChange": 117, "firstSeenPricePercentChange": 10.651284222410377, "firstSeenMaxPricePercentageChange": 15.259923536807532}, {"rank": 10, "chainId": "solana", "coinAddress": "AEh2GCEmBjckprGXgTCB9sGhL7qHz9gYmaGCwoRDAATH", "imgURL": "https://d23exngyjlavgo.cloudfront.net/solana_AEh2GCEmBjckprGXgTCB9sGhL7qHz9gYmaGCwoRDAATH", "name": "All Trump High", "symbol": "ATH", "uniqueName": "all-trump-high-5", "price": 3.009e-05, "price24HChange": 1517.9039301310045, "moralisScore": 68, "buyPressure": -5694.357077416998, "twitterFollowerCount": 251, "volume24H": 119542.598410113, "categories": [], "blockTimestamp": 1731999012, "fullyDilutedValuation": 42086.945195151326, "hypeScore": 27, "marketCap": 42086.945195151326, "firstSeenRank": 368, "firstSeenPrice": 2.5935e-05, "firstSeenTimestampInSeconds": 1737255900, "rankChange": 358, "firstSeenPricePercentChange": 16.020821283979178, "firstSeenMaxPricePercentageChange": 16.020821283979178}]}